{
  "bred_for": "hunting",
  "breed_group": "Hound",
  "caracteristicas_personalidade_nivel_energia": "Elevado",
  "caracteristicas_personalidade_socializacao": "Amigável com pessoas e outros cães",
  "caracteristicas_personalidade_tendencia_latir": "Baixa",
  "caracteristicas_treinamento_facilidade_treino": "Fácil",
  "caracteristicas_treinamento_inteligencia": "Inteligente",
  "caracteristicas_treinamento_tendencia_fugir": "Baixa",
  "cuidados_exercicios": "1 hora por dia",
  "cuidados_grooming": "Monthly Baths",
  "height_imperial": "13",
  "height_metric": "33",
  "highlight_photo": "https://cdn2.thedogapi.com/images/S0_0722_0500.jpg",
  "images": "https://cdn2.thedogapi.com/images/S0_0722_0500.jpg",
  "informacoes_basicas_data_origem": "Século XIX",
  "informacoes_basicas_grupo": "Pastoreio",
  "informacoes_basicas_origem": "Ilhas Shetland",
  "life_span": "12-15 anos",
  "links_referencias": "https://www.akc.org/dog-breeds/shetland-sheepdog/",
  "links_sites_referencia": "https://www.akc.org/dog-breeds/nan-or-142/",
  "links_videos": "https://www.youtube.com/watch?v=q57X8fXi8wM",
  "links_videos_youtube": "https://www.youtube.com/watch?v=q57X8fXi8wM",
  "name": "nan",
  "origin": "United States",
  "reference_image_id": "S0_0722_0500",
  "sobre_aparencia": "Pequeno com uma pelagem dupla longa e densa",
  "sobre_saude": "Suscetível a alguns problemas de saúde",
  "sobre_temperamento": "amigável",
  "temperament": "Amigável",
  "weight_imperial": "4",
  "weight_metric": "18",
  "caracteristicas_fisico_frequencia_queda_pelo": "moderada",
  "caracteristicas_personalidade": "Curious, Independent, Intelligent, Loyal",
  "caracteristicas_treinamento": "Intelligent, Trainable",
  "image": "https://cdn.cdnparenting.com/articles/2020/03/nan-or-106-hero.jpg",
  "**name**": "Pastor-shetland",
  "**group**": "Herding",
  "**origin**": "Shetland Islands, Scotland",
  "**lifespan**": "12-15 years",
  "**weight (kg)**": "13-15",
  "**temperament**": "Friendly, playful, intelligent",
  "**personality**": "Affectionate, loyal, gentle",
  "**colors**": "Black, Blue Merle, Sable",
  "**images**": "https://images.akc.org/breeds/nan_or_142/nan_or_142_01.jpg",
  "**reference links**": "https://www.akc.org/dog-breeds/nan-or-142/",
  "nome": "nan",
  "id": "nan"
}