{
  "nome": "não",
  "caracteristicas_familia_afinidade_com_adultos": "Não encontrei informações sobre a raça nan",
  "caracteristicas_familia_afinidade_com_criancas": "Não encontrei informações sobre a raça nan",
  "caracteristicas_familia_afinidade_com_outros_animais": "Não encontrei informações sobre a raça nan",
  "cuidados_nutricao": "Não encontrei informações sobre a raça nan",
  "cuidados_saude": "Não encontrei informações sobre a raça nan",
  "informacoes_basicas_altura_femea": "Não encontrei informações sobre a raça nan",
  "informacoes_basicas_altura_macho": "Não encontrei informações sobre a raça nan",
  "informacoes_basicas_expectativa_vida": "Não encontrei informações sobre a raça nan",
  "informacoes_basicas_peso_femea": "Não encontrei informações sobre a raça nan",
  "informacoes_basicas_peso_macho": "Não encontrei informações sobre a raça nan",
  "sobre_historia": "Não encontrei informações sobre a raça nan",
  "sobre_temperamento": "Não encontrei informações sobre a raça nan",
  "**name": "Não encontrei informações sobre a raça nan",
  "origin": "Não encontrei informações sobre a raça nan",
  "bred_for": "Não encontrei informações sobre a raça nan",
  "breed_group": "Não encontrei informações sobre a raça nan",
  "caracteristicas_personalidade": "Não encontrei informações sobre a raça nan",
  "caracteristicas_treinamento": "Não encontrei informações sobre a raça nan",
  "cuidados_grooming": "Não encontrei informações sobre a raça nan",
  "height_imperial": "Não encontrei informações sobre a raça nan",
  "height_metric": "Não encontrei informações sobre a raça nan",
  "weight_imperial": "Não encontrei informações sobre a raça nan",
  "weight_metric": "Não encontrei informações sobre a raça nan",
  "id": "nao"
}